hydrogenlib/__init__.py
hydrogenlib/config.py
hydrogenlib/core.py
hydrogenlib/ctypes.py
hydrogenlib/resource_system.py
hydrogenlib/sample.py
hydrogenlib/tools.py
hydrogenlib/winreg.py
hydrogenlib_next-0.6.0.dist-info/METADATA
hydrogenlib_next-0.6.0.dist-info/WHEEL
hydrogenlib_next-0.6.0.dist-info/licenses/License.md
hydrogenlib_next-0.6.0.dist-info/RECORD
