Metadata-Version: 2.4
Name: HydrogenLib-NEXT
Version: 0.6.0
Project-URL: Documentation, https://github.com/LittleNightSong/HydrogenLib#readme
Project-URL: Issues, https://github.com/LittleNightSong/HydrogenLib/issues
Project-URL: Source, https://github.com/LittleNightSong/HydrogenLib
Author-email: LittleNightSong <LittleNightSongYO@outlook.com>
License-File: License.md
Classifier: Development Status :: 3 - Alpha
Classifier: Programming Language :: Python
Classifier: Programming Language :: Python :: 3.11
Classifier: Programming Language :: Python :: 3.12
Classifier: Programming Language :: Python :: 3.13
Classifier: Programming Language :: Python :: 3.14
Classifier: Programming Language :: Python :: Implementation :: CPython
Classifier: Programming Language :: Python :: Implementation :: PyPy
Requires-Python: >=3.12
Requires-Dist: hydrogenlib-config
Requires-Dist: hydrogenlib-core
Requires-Dist: self
